env_suite/__init__.py
env_suite/__version__.py
env_suite/cells.py
env_suite/cli.py
env_suite/ewald.py
env_suite/output.py
env_suite/plotter.py
env_suite/structure.py
env_suite/utils.py
env_suite-0.8.1.dist-info/licenses/LICENSE
env_suite-0.8.1.dist-info/METADATA
env_suite-0.8.1.dist-info/WHEEL
env_suite-0.8.1.dist-info/entry_points.txt
env_suite-0.8.1.dist-info/top_level.txt
env_suite-0.8.1.dist-info/RECORD
