Metadata-Version: 2.4
Name: env_suite
Version: 0.8.1
Summary: A suite of tools for including enviroment effects in first principal calculations
Author: Chilton Group
Author-email: nicholas.chilton@manchester.ac.uk
Classifier: Programming Language :: Python :: 3
Classifier: License :: OSI Approved :: GNU General Public License v3 (GPLv3)
Classifier: Operating System :: OS Independent
Requires-Python: >=3.9
License-File: LICENSE
Requires-Dist: numpy<=1.26.4
Requires-Dist: scipy
Requires-Dist: matplotlib
Requires-Dist: hpc_suite>=1.9.0
Requires-Dist: phonopy
Requires-Dist: pymatgen
Requires-Dist: gaussian_suite
Dynamic: author
Dynamic: author-email
Dynamic: classifier
Dynamic: description
Dynamic: description-content-type
Dynamic: license-file
Dynamic: requires-dist
Dynamic: requires-python
Dynamic: summary
